piweatherrock/GPIOmock.py
piweatherrock/X10.py
piweatherrock/__init__.py
piweatherrock/config.json-sample
piweatherrock/runner.py
piweatherrock/weather.py
piweatherrock/plugin_info/__init__.py
piweatherrock/plugin_weather_common/__init__.py
piweatherrock/plugin_weather_common/icons/256/_nt_spritesheet.png
piweatherrock/plugin_weather_common/icons/256/_spritesheet.png
piweatherrock/plugin_weather_common/icons/256/chanceflurries.png
piweatherrock/plugin_weather_common/icons/256/chancerain.png
piweatherrock/plugin_weather_common/icons/256/chancesleet.png
piweatherrock/plugin_weather_common/icons/256/chancesnow.png
piweatherrock/plugin_weather_common/icons/256/chancetstorms.png
piweatherrock/plugin_weather_common/icons/256/clear.png
piweatherrock/plugin_weather_common/icons/256/cloudy.png
piweatherrock/plugin_weather_common/icons/256/flurries.png
piweatherrock/plugin_weather_common/icons/256/fog.png
piweatherrock/plugin_weather_common/icons/256/hazy.png
piweatherrock/plugin_weather_common/icons/256/mostlycloudy.png
piweatherrock/plugin_weather_common/icons/256/mostlysunny.png
piweatherrock/plugin_weather_common/icons/256/nt_chanceflurries.png
piweatherrock/plugin_weather_common/icons/256/nt_chancerain.png
piweatherrock/plugin_weather_common/icons/256/nt_chancesleet.png
piweatherrock/plugin_weather_common/icons/256/nt_chancesnow.png
piweatherrock/plugin_weather_common/icons/256/nt_chancetstorms.png
piweatherrock/plugin_weather_common/icons/256/nt_clear.png
piweatherrock/plugin_weather_common/icons/256/nt_cloudy.png
piweatherrock/plugin_weather_common/icons/256/nt_flurries.png
piweatherrock/plugin_weather_common/icons/256/nt_fog.png
piweatherrock/plugin_weather_common/icons/256/nt_hazy.png
piweatherrock/plugin_weather_common/icons/256/nt_mostlycloudy.png
piweatherrock/plugin_weather_common/icons/256/nt_mostlysunny.png
piweatherrock/plugin_weather_common/icons/256/nt_partlycloudy.png
piweatherrock/plugin_weather_common/icons/256/nt_partlysunny.png
piweatherrock-2.1.0.dist-info/LICENSE
piweatherrock-2.1.0.dist-info/METADATA
piweatherrock-2.1.0.dist-info/WHEEL
piweatherrock-2.1.0.dist-info/top_level.txt
piweatherrock-2.1.0.dist-info/RECORD
