Metadata-Version: 2.1
Name: piweatherrock
Version: 2.1.0
Summary: Provides forecast data from ClimaCell for PiWeatherRock
Home-page: https://piweatherrock.technicalissues.us
Author: Gene Liverman
Author-email: gene@technicalissues.us
License: MIT
Platform: UNKNOWN
Classifier: License :: OSI Approved :: MIT License
Requires-Python: >=3.6
Requires-Dist: darkskylib
Requires-Dist: pygame
Requires-Dist: pyserial
Requires-Dist: requests
Requires-Dist: cherrypy
Requires-Dist: piweatherrock-webconfig (==1.5.0)
